praating_ai/__init__.py
praating_ai/config.yaml
praating_ai/dictate.py
praating_ai/setup_gui.py
praating_ai/sounds/start.wav
praating_ai/sounds/stop.wav
praating_ai-0.3.0.dist-info/METADATA
praating_ai-0.3.0.dist-info/WHEEL
praating_ai-0.3.0.dist-info/entry_points.txt
praating_ai-0.3.0.dist-info/top_level.txt
praating_ai-0.3.0.dist-info/RECORD
