Metadata-Version: 2.4
Name: praating-ai
Version: 0.3.0
Summary: Push-to-talk voice dictation for Linux using Whisper AI
Author: Frederick van Staden
Project-URL: Homepage, https://github.com/silentFred/praating-ai
Project-URL: Repository, https://github.com/silentFred/praating-ai
Project-URL: Issues, https://github.com/silentFred/praating-ai/issues
Keywords: voice,dictation,whisper,speech-to-text,transcription
Classifier: Development Status :: 4 - Beta
Classifier: Environment :: X11 Applications
Classifier: Intended Audience :: End Users/Desktop
Classifier: Operating System :: POSIX :: Linux
Classifier: Programming Language :: Python :: 3
Classifier: Programming Language :: Python :: 3.8
Classifier: Programming Language :: Python :: 3.9
Classifier: Programming Language :: Python :: 3.10
Classifier: Programming Language :: Python :: 3.11
Classifier: Programming Language :: Python :: 3.12
Classifier: Topic :: Multimedia :: Sound/Audio :: Speech
Requires-Python: >=3.8
Requires-Dist: faster-whisper
Requires-Dist: sounddevice
Requires-Dist: numpy
Requires-Dist: pynput
Requires-Dist: pyyaml
Provides-Extra: cuda
Requires-Dist: nvidia-cudnn-cu12; extra == "cuda"
Requires-Dist: nvidia-cublas-cu12; extra == "cuda"
